odoo8_addon_account_due_list_aging_comments-8.0.0.2.0.99.dev10-py2.7-nspkg.pth
odoo8_addon_account_due_list_aging_comments-8.0.0.2.0.99.dev10.dist-info/DESCRIPTION.rst
odoo8_addon_account_due_list_aging_comments-8.0.0.2.0.99.dev10.dist-info/METADATA
odoo8_addon_account_due_list_aging_comments-8.0.0.2.0.99.dev10.dist-info/RECORD
odoo8_addon_account_due_list_aging_comments-8.0.0.2.0.99.dev10.dist-info/WHEEL
odoo8_addon_account_due_list_aging_comments-8.0.0.2.0.99.dev10.dist-info/metadata.json
odoo8_addon_account_due_list_aging_comments-8.0.0.2.0.99.dev10.dist-info/namespace_packages.txt
odoo8_addon_account_due_list_aging_comments-8.0.0.2.0.99.dev10.dist-info/top_level.txt
odoo_addons/account_due_list_aging_comments/README.rst
odoo_addons/account_due_list_aging_comments/__init__.py
odoo_addons/account_due_list_aging_comments/__openerp__.py
odoo_addons/account_due_list_aging_comments/i18n/de.po
odoo_addons/account_due_list_aging_comments/i18n/es.po
odoo_addons/account_due_list_aging_comments/i18n/fr.po
odoo_addons/account_due_list_aging_comments/i18n/id.po
odoo_addons/account_due_list_aging_comments/i18n/it.po
odoo_addons/account_due_list_aging_comments/i18n/pt_BR.po
odoo_addons/account_due_list_aging_comments/i18n/pt_PT.po
odoo_addons/account_due_list_aging_comments/i18n/ro_RO.po
odoo_addons/account_due_list_aging_comments/i18n/sl.po
odoo_addons/account_due_list_aging_comments/i18n/zh_CN.po
odoo_addons/account_due_list_aging_comments/models/__init__.py
odoo_addons/account_due_list_aging_comments/models/account_move_line.py
odoo_addons/account_due_list_aging_comments/static/description/icon.png
odoo_addons/account_due_list_aging_comments/views/payment_view.xml
