Metadata-Version: 2.0
Name: odoo8-addon-account-due-list-aging-comments
Version: 8.0.0.2.0.99.dev10
Summary: Payments Due list aging comments
Home-page: http://www.eficent.com
Author: Odoo Community Association (OCA), Eficent Business and IT Consulting Services S.L., 
Author-email: support@odoo-community.org
License: AGPL-3
Platform: UNKNOWN
Classifier: Programming Language :: Python
Classifier: Framework :: Odoo
Classifier: License :: OSI Approved :: GNU Affero General Public License v3
Requires-Python: ~=2.7
Requires-Dist: odoo (<9.0a,>=8.0a)
Requires-Dist: odoo8-addon-account-due-list
